aio_upbit/__init__.py
aio_upbit/upbit_rest.py
aio_upbit/upbit_ws.py
aioupbit/__init__.py
aioupbit/rest.py
aioupbit/websocket.py
aioupbit-1.0.0.dist-info/METADATA
aioupbit-1.0.0.dist-info/RECORD
aioupbit-1.0.0.dist-info/WHEEL
aioupbit-1.0.0.dist-info/top_level.txt
